{
  "id": "sr-0-353-961-4",
  "type": "statute",
  "title": "Notenaustausch vom 9. März 1992/11. März 1992 zwischen der Schweiz und Neuseeland zur Bestätigung der Weitergeltung des Auslieferungsvertrags vom 26. November 1880 und des Zusatzabkommens vom 19. Dezember 1934 zwischen der Schweiz und Grossbritannien",
  "title_en": "",
  "short_name": "",
  "status": "in_force",
  "issued_date": "",
  "in_force_date": "",
  "url": "https://www.fedlex.admin.ch/eli/cc/2012/169/en",
  "provisions": [],
  "definitions": []
}