{
  "id": "sr-432-301",
  "type": "statute",
  "title": "Verordnung vom 30. September 2009 über eine Teilinkraftsetzung des Museums- und Sammlungsgesetzes und die Betriebsaufnahme des Schweizerischen Nationalmuseums",
  "title_en": "",
  "short_name": "",
  "status": "in_force",
  "issued_date": "",
  "in_force_date": "",
  "url": "https://www.fedlex.admin.ch/eli/cc/2009/597/en",
  "provisions": [
    {
      "provision_ref": "art1",
      "section": "1",
      "title": "Teilinkraftsetzung",
      "content": "Die Artikel 9–14, 15 Absatz 5, 16 Absatz 3, 18 Absatz 3, 19–22 und 28 MSG treten am 19. Oktober 2009 in Kraft."
    },
    {
      "provision_ref": "art2",
      "section": "2",
      "title": "Befugnisse der Organe des SNM während der Betriebsaufnahme",
      "content": "Die Organe des Schweizerischen Nationalmuseums (SNM) sind befugt, Vorkehrungen zu treffen, die für die Betriebsaufnahme des SNM erforderlich sind. Sie können dazu insbesondere Verträge mit Dritten abschliessen."
    },
    {
      "provision_ref": "art3",
      "section": "3",
      "title": "Finanzierung der Betriebsaufnahme",
      "content": "Die während der Dauer der Betriebsaufnahme entstehenden Kosten des SNM werden vom Bundesamt für Kultur getragen."
    },
    {
      "provision_ref": "art4",
      "section": "4",
      "title": "Inkrafttreten",
      "content": "Diese Verordnung tritt am 19. Oktober 2009 in Kraft."
    }
  ],
  "definitions": []
}