{
  "id": "sr-641-613",
  "type": "statute",
  "title": "Verordnung vom 1. Juli 2020 über die Anpassung der Mineralölsteuersätze für Benzin und Dieselöl",
  "title_en": "",
  "short_name": "",
  "status": "in_force",
  "issued_date": "",
  "in_force_date": "",
  "url": "https://www.fedlex.admin.ch/eli/cc/2020/576/en",
  "provisions": [
    {
      "provision_ref": "art1",
      "section": "1",
      "title": "Steuersätze",
      "content": "1 Für Waren der Zolltarifnummer 2710.1211 (Benzin) beträgt: a. die Mineralölsteuer: Fr. 453.— je 1000 Liter bei 15 °C; b. der Mineralölsteuerzuschlag: Fr. 315.20 je 1000 Liter bei 15 °C. 2 Für Waren der Zolltarifnummern 2710.1912, 2710.1919 und 2710.2010 (Dieselöl) beträgt: a. die Mineralölsteuer: Fr. 481.10 je 1000 Liter bei 15 °C; b. der Mineralölsteuerzuschlag: Fr. 314.60 je 1000 Liter bei 15 °C. SR 632.10 Anhang"
    },
    {
      "provision_ref": "art2",
      "section": "2",
      "title": "Aufhebung eines anderen Erlasses",
      "content": "Die Verordnung vom 30. Januar 2008 über die Anpassung der Mineralölsteuersätze für Benzin wird aufgehoben. [ AS 2008 593 , 2010 3215 , 2011 3331 Anhang 3 Ziff. 14, 2016 2667 Anhang Ziff. 3]"
    },
    {
      "provision_ref": "art3",
      "section": "3",
      "title": "Inkrafttreten",
      "content": "Diese Verordnung tritt am 1. Januar 2021 in Kraft."
    }
  ],
  "definitions": []
}